icebath/__init__.py
icebath-0.0.2.dist-info/licenses/LICENSE
icebath-0.0.2.dist-info/METADATA
icebath-0.0.2.dist-info/WHEEL
icebath-0.0.2.dist-info/top_level.txt
icebath-0.0.2.dist-info/RECORD
