Metadata-Version: 2.4
Name: ICEBath
Version: 0.0.2
Summary: ICESat-2 Calibrated Bathymetry Retrievals from Optical Satellite Data
Home-page: https://github.com/espg/icebath
Author: Shane Grigsby (espg)
Author-email: "Shane Grigsby (espg)" <refuge@rocktalus.com>
License: BSD 3-Clause License
Project-URL: Homepage, https://github.com/espg/ICEBath
Project-URL: Bug Tracker, https://github.com/espg/ICEBath/issues
Keywords: bathymetry,icesat2
Classifier: Programming Language :: Python :: 3
Classifier: License :: OSI Approved :: MIT License
Classifier: Operating System :: OS Independent
Requires-Python: >=3.8
License-File: LICENSE
Requires-Dist: numpy
Requires-Dist: s2cloudless
Requires-Dist: waterdetect
Requires-Dist: pandas
Dynamic: license-file
